ezpredict/__init__.py
ezpredict/predict.py
ezpredict-0.0.6.dist-info/LICENSE
ezpredict-0.0.6.dist-info/METADATA
ezpredict-0.0.6.dist-info/WHEEL
ezpredict-0.0.6.dist-info/top_level.txt
ezpredict-0.0.6.dist-info/RECORD
