Metadata-Version: 2.1
Name: ezpredict
Version: 0.0.6
Summary: A small package for convenient predictions on fine-tuned huggingface-models
Home-page: https://github.com/samueldomdey/ezpredict
Author: Samuel Domdey
Author-email: samuel.domdey@gmail.com
License: UNKNOWN
Project-URL: Bug Tracker, https://github.com/samueldomdey/ezpredict/issues
Platform: UNKNOWN
Classifier: Programming Language :: Python :: 3
Classifier: License :: OSI Approved :: MIT License
Classifier: Operating System :: OS Independent
Requires-Python: >=3.6
License-File: LICENSE
